README.txt
setup.cfg
setup.py
docs/CHANGES.txt
docs/CONTRIBUTORS.txt
docs/HISTORY.txt
docs/INSTALL.txt
docs/LICENSE.GPL
docs/LICENSE.txt
docs/README.txt
pas/__init__.py
pas.plugins.userdeletedevent.egg-info/PKG-INFO
pas.plugins.userdeletedevent.egg-info/SOURCES.txt
pas.plugins.userdeletedevent.egg-info/dependency_links.txt
pas.plugins.userdeletedevent.egg-info/entry_points.txt
pas.plugins.userdeletedevent.egg-info/namespace_packages.txt
pas.plugins.userdeletedevent.egg-info/not-zip-safe
pas.plugins.userdeletedevent.egg-info/paster_plugins.txt
pas.plugins.userdeletedevent.egg-info/requires.txt
pas.plugins.userdeletedevent.egg-info/top_level.txt
pas/plugins/__init__.py
pas/plugins/userdeletedevent/__init__.py
pas/plugins/userdeletedevent/configure.zcml
pas/plugins/userdeletedevent/plugin.py
pas/plugins/userdeletedevent/setuphandlers.py
pas/plugins/userdeletedevent/version.txt
pas/plugins/userdeletedevent/profiles/default/metadata.xml
pas/plugins/userdeletedevent/profiles/default/pas.plugins.userdeletedevent_various.txt
pas/plugins/userdeletedevent/templates/addUserDeletedEventPlugin.zpt