Metadata-Version: 1.0
Name: pas.plugins.userdeletedevent
Version: 0.1
Summary: A PAS plugin for firing events on user deletion
Home-page: https://svn.plone.org/svn/collective/PASPlugins/pas.plugins.userdeletedevent
Author: Simone Orsi [simahawk]
Author-email: simahawk@gmail.com
License: GPL
Platform: UNKNOWN
Classifier: Framework :: Zope2
Classifier: Intended Audience :: Developers
Classifier: Intended Audience :: System Administrators
Classifier: License :: OSI Approved :: GNU General Public License (GPL)
Classifier: Programming Language :: Python
Classifier: Topic :: Software Development :: Libraries :: Python Modules
